sec_edgar_downloader_extended/Downloader.py
sec_edgar_downloader_extended/__init__.py
sec_edgar_downloader_extended/_constants.py
sec_edgar_downloader_extended/_utils.py
sec_edgar_downloader_extended/_version.py
sec_edgar_downloader_extended-4.3.0.dist-info/LICENSE
sec_edgar_downloader_extended-4.3.0.dist-info/METADATA
sec_edgar_downloader_extended-4.3.0.dist-info/WHEEL
sec_edgar_downloader_extended-4.3.0.dist-info/top_level.txt
sec_edgar_downloader_extended-4.3.0.dist-info/RECORD
