Metadata-Version: 2.1
Name: sec-edgar-downloader-extended
Version: 4.3.0
Summary: Extended version of https://github.com/jadchaar/sec-edgar-downloader by Jad Chaar.Download SEC filings from the EDGAR database using Python. All credits go to him for this work, I justmade a few minor amendments needed for a personal project
Home-page: https://github.com/jadchaar/sec-edgar-downloader-extended
Author: Greg Bland
Author-email: gbland94@hotmail.com
License: MIT
Keywords: sec edgar filing financial finance stocks mutual-funds sec.gov
Classifier: Development Status :: 5 - Production/Stable
Classifier: Intended Audience :: Developers
Classifier: Intended Audience :: Information Technology
Classifier: Intended Audience :: Financial and Insurance Industry
Classifier: Natural Language :: English
Classifier: Topic :: Software Development :: Libraries :: Python Modules
Classifier: Topic :: Office/Business :: Financial
Classifier: Topic :: Office/Business :: Financial :: Investment
Classifier: License :: OSI Approved :: MIT License
Classifier: Programming Language :: Python :: 3
Classifier: Programming Language :: Python :: 3.6
Classifier: Programming Language :: Python :: 3.7
Classifier: Programming Language :: Python :: 3.8
Classifier: Programming Language :: Python :: 3.9
Classifier: Programming Language :: Python :: 3.10
Classifier: Programming Language :: Python :: 3 :: Only
Classifier: Operating System :: OS Independent
Requires-Python: >=3.6
License-File: LICENSE
Requires-Dist: requests
Requires-Dist: bs4
Requires-Dist: lxml
Requires-Dist: Faker
